psql_to_csv/__init__.py
psql_to_csv-0.1.dist-info/DESCRIPTION.rst
psql_to_csv-0.1.dist-info/entry_points.txt
psql_to_csv-0.1.dist-info/METADATA
psql_to_csv-0.1.dist-info/metadata.json
psql_to_csv-0.1.dist-info/RECORD
psql_to_csv-0.1.dist-info/top_level.txt
psql_to_csv-0.1.dist-info/WHEEL
