Metadata-Version: 2.0
Name: psql-to-csv
Version: 0.1
Summary: when you forget to properly format the results of a query that takes forever
Home-page: http://github.com/eriktaubeneck/psql_to_csv
Author: Erik Taubeneck
Author-email: erik.taubeneck@gmail.com
License: MIT
Platform: any
Classifier: Development Status :: 3 - Alpha
Classifier: Intended Audience :: Developers
Classifier: License :: OSI Approved :: MIT License
Classifier: Natural Language :: English 
Classifier: Operating System :: OS Independent
Classifier: Programming Language :: Python :: 2
Classifier: Topic :: Software Development :: Build Tools
Classifier: Topic :: Software Development :: Libraries :: Python Modules
Requires-Dist: docopt (>=0.6)
